primawera/__init__.py
primawera/app.py
primawera/filters.py
primawera/html_codes.py
primawera/loading.py
primawera/lut.py
primawera/modeutils.py
primawera/luts/grayscale.lut
primawera/luts/jet.lut
primawera/luts/sepia.lut
primawera/widgets/HighlightScrollArea.py
primawera/widgets/__init__.py
primawera/widgets/canvas2d.py
primawera/widgets/canvas3d.py
primawera/widgets/canvasbase.py
primawera/widgets/canvascomplex.py
primawera/widgets/informationwindow.py
primawera/widgets/pixmaplabel.py
primawera/widgets/previewwindow.py
primawera/widgets/visualiser.py
primawera-0.6.1.dist-info/COPYING.txt
primawera-0.6.1.dist-info/METADATA
primawera-0.6.1.dist-info/WHEEL
primawera-0.6.1.dist-info/entry_points.txt
primawera-0.6.1.dist-info/top_level.txt
primawera-0.6.1.dist-info/RECORD
