Metadata-Version: 2.1
Name: primawera
Version: 0.6.1
Summary: Simple image viewer with 3D, complex and floating images support.
Author-email: Bruno Petrus <xpetrus@fi.muni.cz>
Project-URL: Source, https://gitlab.fi.muni.cz/xpetrus/primawera
Project-URL: Bug tracker, https://gitlab.fi.muni.cz/xpetrus/primawera/-/issues
Classifier: Programming Language :: Python :: 3
Classifier: License :: OSI Approved :: GNU General Public License v3 (GPLv3)
Classifier: Development Status :: 3 - Alpha
Classifier: Operating System :: OS Independent
Requires-Python: >=3.11
License-File: COPYING.txt
Requires-Dist: numpy >=2.1.0
Requires-Dist: Pillow >=10.4.0
Requires-Dist: PyQt5 >=5.15.9
Requires-Dist: h5py >=3.7
